tikfo/__init__.py
tikfo/cli.py
tikfo/info.py
tikfo-0.0.1.dist-info/licenses/LICENSE
tikfo-0.0.1.dist-info/WHEEL
tikfo-0.0.1.dist-info/METADATA
tikfo-0.0.1.dist-info/RECORD
