Metadata-Version: 2.4
Name: tikfo
Version: 0.0.1
Summary: TikTok Info: Module for retrieving and processing information from TikTok.
Author-email: BilalsBxp <bilalsaputra641@gmail.com>
License-Expression: MIT
License-File: LICENSE
